[
  {
    "ts": "2025-11-05T16:38:28+00:00",
    "headline": "Earnings beat helps Expeditors stock power to an all-time high",
    "summary": "Expeditors stock is on a roll after earnings that beat expectations. The post Earnings beat helps Expeditors stock power to an all-time high appeared first on FreightWaves.",
    "url": "https://finance.yahoo.com/news/earnings-beat-helps-expeditors-stock-163828333.html",
    "source": "FreightWaves",
    "provider": "yfinance",
    "raw": {
      "id": "2905fd8a-dba1-3bb4-85ee-24e10a667a94",
      "content": {
        "id": "2905fd8a-dba1-3bb4-85ee-24e10a667a94",
        "contentType": "STORY",
        "title": "Earnings beat helps Expeditors stock power to an all-time high",
        "description": "",
        "summary": "Expeditors stock is on a roll after earnings that beat expectations. The post Earnings beat helps Expeditors stock power to an all-time high appeared first on FreightWaves.",
        "pubDate": "2025-11-05T16:38:28Z",
        "displayTime": "2025-11-05T16:38:28Z",
        "isHosted": true,
        "bypassModal": false,
        "previewUrl": null,
        "thumbnail": {
          "originalUrl": "https://media.zenfs.com/en/freightwaves_373/8a7cb42e4376b02016cb11ae29e6ceda",
          "originalWidth": 1088,
          "originalHeight": 557,
          "caption": "",
          "resolutions": [
            {
              "url": "https://s.yimg.com/uu/api/res/1.2/1eqw3MLwIk8vL6ccV5.HKg--~B/aD01NTc7dz0xMDg4O2FwcGlkPXl0YWNoeW9u/https://media.zenfs.com/en/freightwaves_373/8a7cb42e4376b02016cb11ae29e6ceda.cf.webp",
              "width": 1088,
              "height": 557,
              "tag": "original"
            },
            {
              "url": "https://s.yimg.com/uu/api/res/1.2/HvGTPsTreTbHgVEvF3Micg--~B/Zmk9c3RyaW07aD0xMjg7dz0xNzA7YXBwaWQ9eXRhY2h5b24-/https://media.zenfs.com/en/freightwaves_373/8a7cb42e4376b02016cb11ae29e6ceda.cf.webp",
              "width": 170,
              "height": 128,
              "tag": "170x128"
            }
          ]
        },
        "provider": {
          "displayName": "FreightWaves",
          "url": "https://www.freightwaves.com"
        },
        "canonicalUrl": {
          "url": "https://finance.yahoo.com/news/earnings-beat-helps-expeditors-stock-163828333.html",
          "site": "finance",
          "region": "US",
          "lang": "en-US"
        },
        "clickThroughUrl": {
          "url": "https://finance.yahoo.com/news/earnings-beat-helps-expeditors-stock-163828333.html",
          "site": "finance",
          "region": "US",
          "lang": "en-US"
        },
        "metadata": {
          "editorsPick": false
        },
        "finance": {
          "stockTickers": [
            {
              "symbol": "EXPD"
            }
          ],
          "premiumFinance": {
            "isPremiumNews": false,
            "isPremiumFreeNews": false
          }
        },
        "storyline": null
      }
    }
  },
  {
    "ts": "2025-11-05T18:19:37+00:00",
    "headline": "3 Profitable Stocks That Fall Short",
    "summary": "While profitability is essential, it doesn’t guarantee long-term success. Some companies that rest on their margins will lose ground as competition intensifies - as Jeff Bezos said, \"Your margin is my opportunity\".",
    "url": "https://finance.yahoo.com/news/3-profitable-stocks-fall-short-181937195.html",
    "source": "StockStory",
    "provider": "yfinance",
    "raw": {
      "id": "3b2b0565-93c8-3835-8551-a299d21f4d7d",
      "content": {
        "id": "3b2b0565-93c8-3835-8551-a299d21f4d7d",
        "contentType": "STORY",
        "title": "3 Profitable Stocks That Fall Short",
        "description": "",
        "summary": "While profitability is essential, it doesn’t guarantee long-term success. Some companies that rest on their margins will lose ground as competition intensifies - as Jeff Bezos said, \"Your margin is my opportunity\".",
        "pubDate": "2025-11-05T18:19:37Z",
        "displayTime": "2025-11-05T18:19:37Z",
        "isHosted": true,
        "bypassModal": false,
        "previewUrl": null,
        "thumbnail": {
          "originalUrl": "https://media.zenfs.com/en/stockstory_922/68c15dc93de992b951773b2e1b57bb3c",
          "originalWidth": 1400,
          "originalHeight": 700,
          "caption": "BBWI Cover Image",
          "resolutions": [
            {
              "url": "https://s.yimg.com/uu/api/res/1.2/oGJH3Da96zx9GPa5u22zDQ--~B/aD03MDA7dz0xNDAwO2FwcGlkPXl0YWNoeW9u/https://media.zenfs.com/en/stockstory_922/68c15dc93de992b951773b2e1b57bb3c.cf.webp",
              "width": 1400,
              "height": 700,
              "tag": "original"
            },
            {
              "url": "https://s.yimg.com/uu/api/res/1.2/WW91dJSqj7Pad3vFg3okWA--~B/Zmk9c3RyaW07aD0xMjg7dz0xNzA7YXBwaWQ9eXRhY2h5b24-/https://media.zenfs.com/en/stockstory_922/68c15dc93de992b951773b2e1b57bb3c.cf.webp",
              "width": 170,
              "height": 128,
              "tag": "170x128"
            }
          ]
        },
        "provider": {
          "displayName": "StockStory",
          "url": "https://stockstory.org/"
        },
        "canonicalUrl": {
          "url": "https://finance.yahoo.com/news/3-profitable-stocks-fall-short-181937195.html",
          "site": "finance",
          "region": "US",
          "lang": "en-US"
        },
        "clickThroughUrl": {
          "url": "https://finance.yahoo.com/news/3-profitable-stocks-fall-short-181937195.html",
          "site": "finance",
          "region": "US",
          "lang": "en-US"
        },
        "metadata": {
          "editorsPick": false
        },
        "finance": {
          "stockTickers": [
            {
              "symbol": "BBWI"
            },
            {
              "symbol": "EXPD"
            },
            {
              "symbol": "HGV"
            }
          ],
          "premiumFinance": {
            "isPremiumNews": false,
            "isPremiumFreeNews": false
          }
        },
        "storyline": null
      }
    }
  }
]