[
  {
    "ts": "2025-04-06T12:59:47+00:00",
    "headline": "Is Cincinnati Financial Corporation (CINF) the Best Dividend King to Buy for Safe Dividend Growth?",
    "summary": "We recently published a list of the 12 Best Dividend Kings to Buy For Safe Dividend Growth. In this article, we are going to take a look at where Cincinnati Financial Corporation (NASDAQ:CINF) stands against other best dividend kings. The importance of dividend stocks cannot be denied, even in today’s market environment, which is dominated […]",
    "url": "https://finance.yahoo.com/news/cincinnati-financial-corporation-cinf-best-125947222.html",
    "source": "Insider Monkey",
    "provider": "yfinance",
    "raw": {
      "id": "69c03313-b5a2-3000-b02d-c7f45d6be81b",
      "content": {
        "id": "69c03313-b5a2-3000-b02d-c7f45d6be81b",
        "contentType": "STORY",
        "title": "Is Cincinnati Financial Corporation (CINF) the Best Dividend King to Buy for Safe Dividend Growth?",
        "description": "",
        "summary": "We recently published a list of the 12 Best Dividend Kings to Buy For Safe Dividend Growth. In this article, we are going to take a look at where Cincinnati Financial Corporation (NASDAQ:CINF) stands against other best dividend kings. The importance of dividend stocks cannot be denied, even in today’s market environment, which is dominated […]",
        "pubDate": "2025-04-06T12:59:47Z",
        "displayTime": "2025-04-06T12:59:47Z",
        "isHosted": true,
        "bypassModal": false,
        "previewUrl": null,
        "thumbnail": {
          "originalUrl": "https://media.zenfs.com/en/insidermonkey.com/c824f48499a59fe5612c48099a4f66a7",
          "originalWidth": 1456,
          "originalHeight": 816,
          "caption": "Is Cincinnati Financial Corporation (CINF) the Best Dividend King to Buy for Safe Dividend Growth?",
          "resolutions": [
            {
              "url": "https://s.yimg.com/uu/api/res/1.2/7UKnDFPonz2EtjuT49aolg--~B/aD04MTY7dz0xNDU2O2FwcGlkPXl0YWNoeW9u/https://media.zenfs.com/en/insidermonkey.com/c824f48499a59fe5612c48099a4f66a7.cf.webp",
              "width": 1456,
              "height": 816,
              "tag": "original"
            },
            {
              "url": "https://s.yimg.com/uu/api/res/1.2/sO1QiKZnhVk9xCp5BcwRDw--~B/Zmk9c3RyaW07aD0xMjg7dz0xNzA7YXBwaWQ9eXRhY2h5b24-/https://media.zenfs.com/en/insidermonkey.com/c824f48499a59fe5612c48099a4f66a7.cf.webp",
              "width": 170,
              "height": 128,
              "tag": "170x128"
            }
          ]
        },
        "provider": {
          "displayName": "Insider Monkey",
          "url": "http://www.insidermonkey.com"
        },
        "canonicalUrl": {
          "url": "https://finance.yahoo.com/news/cincinnati-financial-corporation-cinf-best-125947222.html",
          "site": "finance",
          "region": "US",
          "lang": "en-US"
        },
        "clickThroughUrl": {
          "url": "https://finance.yahoo.com/news/cincinnati-financial-corporation-cinf-best-125947222.html",
          "site": "finance",
          "region": "US",
          "lang": "en-US"
        },
        "metadata": {
          "editorsPick": false
        },
        "finance": {
          "stockTickers": [
            {
              "symbol": "CINF"
            }
          ],
          "premiumFinance": {
            "isPremiumNews": false,
            "isPremiumFreeNews": false
          }
        },
        "storyline": null
      }
    }
  }
]