[
  {
    "ts": null,
    "headline": "Dow's nearly 600-point rally led by gains for Caterpillar, Microsoft stocks",
    "summary": "Dow's nearly 600-point rally led by gains for Caterpillar, Microsoft stocks",
    "url": "https://finnhub.io/api/news?id=81e89f35d6261cbf1bf18f68f20315094b10be6b45e617a4a715b67f1db19283",
    "source": "MarketWatch",
    "provider": "finnhub",
    "raw": {
      "category": "company",
      "datetime": 1741187040,
      "headline": "Dow's nearly 600-point rally led by gains for Caterpillar, Microsoft stocks",
      "id": 133052096,
      "image": "",
      "related": "BA",
      "source": "MarketWatch",
      "summary": "Dow's nearly 600-point rally led by gains for Caterpillar, Microsoft stocks",
      "url": "https://finnhub.io/api/news?id=81e89f35d6261cbf1bf18f68f20315094b10be6b45e617a4a715b67f1db19283"
    }
  },
  {
    "ts": null,
    "headline": "Caterpillar, Boeing share gains lead Dow's 429-point rally",
    "summary": "Caterpillar, Boeing share gains lead Dow's 429-point rally",
    "url": "https://finnhub.io/api/news?id=0d5b0636a48216779ae0a972ae27251e7060e2df3b1b828649b484d9360c3e4e",
    "source": "MarketWatch",
    "provider": "finnhub",
    "raw": {
      "category": "company",
      "datetime": 1741183380,
      "headline": "Caterpillar, Boeing share gains lead Dow's 429-point rally",
      "id": 133019031,
      "image": "",
      "related": "BA",
      "source": "MarketWatch",
      "summary": "Caterpillar, Boeing share gains lead Dow's 429-point rally",
      "url": "https://finnhub.io/api/news?id=0d5b0636a48216779ae0a972ae27251e7060e2df3b1b828649b484d9360c3e4e"
    }
  },
  {
    "ts": null,
    "headline": "Dow's 300-point rally highlighted by gains in Caterpillar, Boeing stocks",
    "summary": "Dow's 300-point rally highlighted by gains in Caterpillar, Boeing stocks",
    "url": "https://finnhub.io/api/news?id=8c2bffb9b1d6068b306c2e314ff4477b72ceb6b5d091043ec48ed44fb2414783",
    "source": "MarketWatch",
    "provider": "finnhub",
    "raw": {
      "category": "company",
      "datetime": 1741179060,
      "headline": "Dow's 300-point rally highlighted by gains in Caterpillar, Boeing stocks",
      "id": 133016655,
      "image": "",
      "related": "BA",
      "source": "MarketWatch",
      "summary": "Dow's 300-point rally highlighted by gains in Caterpillar, Boeing stocks",
      "url": "https://finnhub.io/api/news?id=8c2bffb9b1d6068b306c2e314ff4477b72ceb6b5d091043ec48ed44fb2414783"
    }
  }
]