[
  {
    "ts": null,
    "headline": "Materials Dividends Spotlight: Dow’s (DOW) Consistent Payout and Growth Strategy",
    "summary": "Dow Inc. (NYSE:DOW) is included among the 13 Best Materials Dividend Stocks to Buy Right Now. Dow Inc. (NYSE:DOW) is a major global player in materials science and chemicals, providing products and solutions to various industries, including packaging and infrastructure. The company has a broad international presence and manufactures a wide array of chemical, plastic, […]",
    "url": "https://finnhub.io/api/news?id=7b215c2a81e495dfe9b8409e2a072b9a6fa9d965658ad4d5127893a764af27af",
    "source": "Yahoo",
    "provider": "finnhub",
    "raw": {
      "category": "company",
      "datetime": 1754004539,
      "headline": "Materials Dividends Spotlight: Dow’s (DOW) Consistent Payout and Growth Strategy",
      "id": 136161574,
      "image": "https://s.yimg.com/rz/stage/p/yahoo_finance_en-US_h_p_finance_2.png",
      "related": "DOW",
      "source": "Yahoo",
      "summary": "Dow Inc. (NYSE:DOW) is included among the 13 Best Materials Dividend Stocks to Buy Right Now. Dow Inc. (NYSE:DOW) is a major global player in materials science and chemicals, providing products and solutions to various industries, including packaging and infrastructure. The company has a broad international presence and manufactures a wide array of chemical, plastic, […]",
      "url": "https://finnhub.io/api/news?id=7b215c2a81e495dfe9b8409e2a072b9a6fa9d965658ad4d5127893a764af27af"
    }
  },
  {
    "ts": null,
    "headline": "Franklin Biotechnology Discovery Fund Q2 2025 Commentary",
    "summary": "Franklin Templetonâs Biotechnology Discovery Fund sees long-term potential despite Q2 losses. Explore how innovation and AI are shaping its outlook.",
    "url": "https://finnhub.io/api/news?id=d61632bb7ac932a66ab21f6c57260f4bb79e88518f44428ce4f279a1392e761e",
    "source": "SeekingAlpha",
    "provider": "finnhub",
    "raw": {
      "category": "company",
      "datetime": 1753997700,
      "headline": "Franklin Biotechnology Discovery Fund Q2 2025 Commentary",
      "id": 136159393,
      "image": "https://static.seekingalpha.com/cdn/s3/uploads/getty_images/1408826216/image_1408826216.jpg?io=getty-c-w1536",
      "related": "DOW",
      "source": "SeekingAlpha",
      "summary": "Franklin Templetonâs Biotechnology Discovery Fund sees long-term potential despite Q2 losses. Explore how innovation and AI are shaping its outlook.",
      "url": "https://finnhub.io/api/news?id=d61632bb7ac932a66ab21f6c57260f4bb79e88518f44428ce4f279a1392e761e"
    }
  },
  {
    "ts": null,
    "headline": "Franklin Small Cap Growth Fund Q2 2025 Commentary",
    "summary": "Franklin Small Cap Growth Fund Q2 2025 Commentary",
    "url": "https://finnhub.io/api/news?id=f1ebd25213882ba1de0d0d87fd8e8efb539fc3b6b2c8aa8b141925d99b05c2c8",
    "source": "SeekingAlpha",
    "provider": "finnhub",
    "raw": {
      "category": "company",
      "datetime": 1753989900,
      "headline": "Franklin Small Cap Growth Fund Q2 2025 Commentary",
      "id": 136158922,
      "image": "",
      "related": "DOW",
      "source": "SeekingAlpha",
      "summary": "",
      "url": "https://finnhub.io/api/news?id=f1ebd25213882ba1de0d0d87fd8e8efb539fc3b6b2c8aa8b141925d99b05c2c8"
    }
  },
  {
    "ts": null,
    "headline": "Jim Cramer on Dow: “The Stock Was Screaming My Yield’s Unsafe”",
    "summary": "Dow Inc. (NYSE:DOW) is one of the stocks Jim Cramer shared insights on. During the episode, Cramer discussed the stock’s dividend. He commented: “A dividend sucker is born every minute. Last week, chemical giant Dow cut its dividend in half, taking it from 70 cents per quarter to 35 cents, saving about $1 billion annually… […]",
    "url": "https://finnhub.io/api/news?id=b591318788621f84db186f5fa57920cd2ac200551726f6219df739e603e19dca",
    "source": "Yahoo",
    "provider": "finnhub",
    "raw": {
      "category": "company",
      "datetime": 1753987991,
      "headline": "Jim Cramer on Dow: “The Stock Was Screaming My Yield’s Unsafe”",
      "id": 136161575,
      "image": "https://s.yimg.com/rz/stage/p/yahoo_finance_en-US_h_p_finance_2.png",
      "related": "DOW",
      "source": "Yahoo",
      "summary": "Dow Inc. (NYSE:DOW) is one of the stocks Jim Cramer shared insights on. During the episode, Cramer discussed the stock’s dividend. He commented: “A dividend sucker is born every minute. Last week, chemical giant Dow cut its dividend in half, taking it from 70 cents per quarter to 35 cents, saving about $1 billion annually… […]",
      "url": "https://finnhub.io/api/news?id=b591318788621f84db186f5fa57920cd2ac200551726f6219df739e603e19dca"
    }
  },
  {
    "ts": null,
    "headline": "Franklin DynaTech SMA Q2 2025 Commentary",
    "summary": "Franklin Templeton reports strong Q2 gains led by tech and selective stock picks. See how AI and innovation are shaping their outlook. Read the full update.",
    "url": "https://finnhub.io/api/news?id=7c93f3541e894bd4df214dac6bf5adfc913915794a006af96ff664728b295780",
    "source": "SeekingAlpha",
    "provider": "finnhub",
    "raw": {
      "category": "company",
      "datetime": 1753959600,
      "headline": "Franklin DynaTech SMA Q2 2025 Commentary",
      "id": 136154182,
      "image": "https://static.seekingalpha.com/cdn/s3/uploads/getty_images/974479826/image_974479826.jpg?io=getty-c-w1536",
      "related": "DOW",
      "source": "SeekingAlpha",
      "summary": "Franklin Templeton reports strong Q2 gains led by tech and selective stock picks. See how AI and innovation are shaping their outlook. Read the full update.",
      "url": "https://finnhub.io/api/news?id=7c93f3541e894bd4df214dac6bf5adfc913915794a006af96ff664728b295780"
    }
  },
  {
    "ts": null,
    "headline": "Franklin Small Cap Growth SMA Q2 2025 Commentary",
    "summary": "Franklin Templeton sees opportunity in AI, industrials, and health care amid market volatility. Explore their Q2 outlook and strategy for long-term growth.",
    "url": "https://finnhub.io/api/news?id=ab9fe8d15046d81dab56b3c2880480d9ad3e4862fafa9b9df109ed1e9e5dee85",
    "source": "SeekingAlpha",
    "provider": "finnhub",
    "raw": {
      "category": "company",
      "datetime": 1753941600,
      "headline": "Franklin Small Cap Growth SMA Q2 2025 Commentary",
      "id": 136150750,
      "image": "https://static.seekingalpha.com/cdn/s3/uploads/getty_images/2185253233/image_2185253233.jpg?io=getty-c-w1536",
      "related": "DOW",
      "source": "SeekingAlpha",
      "summary": "Franklin Templeton sees opportunity in AI, industrials, and health care amid market volatility. Explore their Q2 outlook and strategy for long-term growth.",
      "url": "https://finnhub.io/api/news?id=ab9fe8d15046d81dab56b3c2880480d9ad3e4862fafa9b9df109ed1e9e5dee85"
    }
  }
]