[
  {
    "ts": null,
    "headline": "Deadline Alert: Block, Inc. (SQ, XYZ) Investors Who Lost Money Urged To Contact Glancy Prongay & Murray LLP About Securities Fraud Lawsuit",
    "summary": "Glancy Prongay & Murray LLP reminds investors of the upcoming March 18, 2025 deadline to file a lead plaintiff motion in the class action filed on behalf of investors who purchased or otherwise...",
    "url": "https://finnhub.io/api/news?id=ba2bae690b71860be888caa312f7028e0c8d2ea70d771add2632bb1d3cfb7d1a",
    "source": "Finnhub",
    "provider": "finnhub",
    "raw": {
      "category": "company",
      "datetime": 1737720069,
      "headline": "Deadline Alert: Block, Inc. (SQ, XYZ) Investors Who Lost Money Urged To Contact Glancy Prongay & Murray LLP About Securities Fraud Lawsuit",
      "id": 132455514,
      "image": "",
      "related": "XYZ",
      "source": "Finnhub",
      "summary": "Glancy Prongay & Murray LLP reminds investors of the upcoming March 18, 2025 deadline to file a lead plaintiff motion in the class action filed on behalf of investors who purchased or otherwise...",
      "url": "https://finnhub.io/api/news?id=ba2bae690b71860be888caa312f7028e0c8d2ea70d771add2632bb1d3cfb7d1a"
    }
  },
  {
    "ts": null,
    "headline": "SQ Investors Have Opportunity to Lead Block, Inc. Securities Fraud Lawsuit",
    "summary": "NEW YORK, Jan. 24, 2025 /PRNewswire/ --  Why: Rosen Law Firm, a global investor...",
    "url": "https://finnhub.io/api/news?id=a64a2107b8f2341ddabeefa27ce545e6b2e6a06440034749cd6a48d622102246",
    "source": "Finnhub",
    "provider": "finnhub",
    "raw": {
      "category": "company",
      "datetime": 1737680466,
      "headline": "SQ Investors Have Opportunity to Lead Block, Inc. Securities Fraud Lawsuit",
      "id": 132452488,
      "image": "",
      "related": "XYZ",
      "source": "Finnhub",
      "summary": "NEW YORK, Jan. 24, 2025 /PRNewswire/ --  Why: Rosen Law Firm, a global investor...",
      "url": "https://finnhub.io/api/news?id=a64a2107b8f2341ddabeefa27ce545e6b2e6a06440034749cd6a48d622102246"
    }
  }
]